pyscdi/__init__.py
pyscdi/main.py
pyscdi/settings.py
pyscdi/utils.py
pyscdi-0.2.2.dist-info/METADATA
pyscdi-0.2.2.dist-info/RECORD
pyscdi-0.2.2.dist-info/WHEEL
pyscdi-0.2.2.dist-info/top_level.txt
