Metadata-Version: 2.1
Name: pyscdi
Version: 0.2.2
Summary: Python binding for SCDI
Home-page: http://github.com/sunsern/scdi-python
Author: Sunsern Cheamanunkul
Author-email: sunsern@gmail.com
License: MIT
Platform: UNKNOWN
Requires-Dist: requests
